.gitignore
.travis.yml
build_test.sh
header.py
setup.py
test.py
testing.ini.gpg
docs/Makefile
docs/make.bat
docs/source/CHANGES.rst
docs/source/README.rst
docs/source/conf.py
docs/source/index.rst
pp/__init__.py
pp.core.egg-info/PKG-INFO
pp.core.egg-info/SOURCES.txt
pp.core.egg-info/dependency_links.txt
pp.core.egg-info/entry_points.txt
pp.core.egg-info/namespace_packages.txt
pp.core.egg-info/not-zip-safe
pp.core.egg-info/requires.txt
pp.core.egg-info/top_level.txt
pp/core/__init__.py
pp/core/conversion.py
pp/core/fslayer.py
pp/core/logger.py
pp/core/resource.py
pp/core/resources_registry.py
pp/core/transformation.py
pp/core/util.py
pp/core/samples/demo.html
pp/core/tests/__init__.py
pp/core/tests/fs_base.py
pp/core/tests/test_resource.py
pp/core/tests/test_resources_registry.py
pp/core/tests/test_transformation.py
pp/core/tests/test_util.py
pp/core/tests/example_resource/demo.css
pp/core/tests/example_resource/demo.pt
pp/core/tests/sampledata/1.html
pp/core/tests/sampledata/2.html
pp/core/tests/sampledata/3.html