Metadata-Version: 2.1
Name: pp.core
Version: 0.4.4
Summary: pp.core
Home-page: http://pypi.python.org/pypi/pp.core
Author: Andreas Jung
Author-email: info@zopyx.com
License: UNKNOWN
Keywords: Python Produce & Publish
Platform: UNKNOWN
Classifier: Programming Language :: Python
Classifier: Programming Language :: Python :: 2.7
Classifier: Programming Language :: Python :: 3.6
Classifier: Programming Language :: Python :: 3.7
Provides-Extra: testing
